mercury_agent/__init__.py
mercury_agent/agent.py
mercury_agent/backend_client.py
mercury_agent/capabilities.py
mercury_agent/configuration.py
mercury_agent/pong.py
mercury_agent/register.py
mercury_agent/remote_logging.py
mercury_agent/rpc.py
mercury_agent/task_runner.py
mercury_agent/hardware/__init__.py
mercury_agent/hardware/platform_detection.py
mercury_agent/hardware/drivers/__init__.py
mercury_agent/hardware/drivers/drivers.py
mercury_agent/hardware/drivers/hp_raid.py
mercury_agent/hardware/drivers/megaraid.py
mercury_agent/hardware/drivers/obm.py
mercury_agent/hardware/erase/__init__.py
mercury_agent/hardware/erase/os_level_erase.py
mercury_agent/hardware/general/__init__.py
mercury_agent/hardware/general/mcelog.py
mercury_agent/hardware/obm/__init__.py
mercury_agent/hardware/obm/ipmitool.py
mercury_agent/hardware/obm/racadm.py
mercury_agent/hardware/oem/__init__.py
mercury_agent/hardware/oem/dell/__init__.py
mercury_agent/hardware/oem/dell/om_xml_deserializer.py
mercury_agent/hardware/oem/dell/omreport.py
mercury_agent/hardware/oem/hp/__init__.py
mercury_agent/hardware/oem/hp/hpasmcli.py
mercury_agent/hardware/raid/__init__.py
mercury_agent/hardware/raid/abstraction/__init__.py
mercury_agent/hardware/raid/abstraction/api.py
mercury_agent/hardware/raid/interfaces/__init__.py
mercury_agent/hardware/raid/interfaces/mapping.py
mercury_agent/hardware/raid/interfaces/megaraid/__init__.py
mercury_agent/hardware/raid/interfaces/megaraid/megacli.py
mercury_agent/hardware/raid/interfaces/megaraid/storcli.py
mercury_agent/inspector/__init__.py
mercury_agent/inspector/inspect.py
mercury_agent/inspector/hwlib/__init__.py
mercury_agent/inspector/hwlib/biosdevname.py
mercury_agent/inspector/hwlib/cpuinfo.py
mercury_agent/inspector/hwlib/iproute2.py
mercury_agent/inspector/hwlib/lspci.py
mercury_agent/inspector/hwlib/meminfo.py
mercury_agent/inspector/hwlib/mercury_id.py
mercury_agent/inspector/hwlib/network_interfaces.py
mercury_agent-0.1.10.dist-info/DESCRIPTION.rst
mercury_agent-0.1.10.dist-info/METADATA
mercury_agent-0.1.10.dist-info/RECORD
mercury_agent-0.1.10.dist-info/WHEEL
mercury_agent-0.1.10.dist-info/entry_points.txt
mercury_agent-0.1.10.dist-info/metadata.json
mercury_agent-0.1.10.dist-info/top_level.txt
