Metadata-Version: 2.0
Name: mercury-agent
Version: 0.1.10
Summary: Mercury agent, hardware libraries, and inspectors
Home-page: http://www.mercurysoft.io
Author: Jared Rodriguez
Author-email: jared.rodriguez@rackspace.com
License: Apache-2.0
Platform: UNKNOWN
Requires-Dist: mercury-core
Requires-Dist: netifaces
Requires-Dist: pyudev
Requires-Dist: python-hpssa
Requires-Dist: lxml
Requires-Dist: press
Requires-Dist: six
Requires-Dist: msgpack-python
Requires-Dist: pyzmq
